example/__init__.py
seaweedfs/__init__.py
seaweedfs/client.py
seaweedfs/exceptions.py
tests/__init__.py
tests/test_filer.py
seaweedfs_py-1.0.0.dist-info/LICENSE
seaweedfs_py-1.0.0.dist-info/METADATA
seaweedfs_py-1.0.0.dist-info/WHEEL
seaweedfs_py-1.0.0.dist-info/top_level.txt
seaweedfs_py-1.0.0.dist-info/RECORD
