Metadata-Version: 2.1
Name: seaweedfs-py
Version: 1.0.0
Summary: client of seaweedfs
Home-page: https://github.com/GeorgeWang1994/seaweedfs-py
Author: george wang
Author-email: georgewang1994@163.com
License: UNKNOWN
Platform: UNKNOWN
Classifier: Development Status :: 5 - Production/Stable
Classifier: Environment :: Web Environment
Classifier: Intended Audience :: Developers
Classifier: License :: OSI Approved :: MIT License
Classifier: Operating System :: OS Independent
Classifier: Programming Language :: Python
Classifier: Programming Language :: Python :: 3.4
Classifier: Programming Language :: Python :: 3.5
Classifier: Programming Language :: Python :: 3.6
Classifier: Programming Language :: Python :: 3.7
Requires-Dist: requests (==2.22.0)
Requires-Dist: pytest (==5.2.4)
